frozen_soup/__init__.py
frozen_soup/__main__.py
frozen_soup/css/__init__.py
frozen_soup/resource/__init__.py
frozen_soup/server/__init__.py
frozen_soup/server/__main__.py
frozen_soup-0.5.dist-info/LICENSE
frozen_soup-0.5.dist-info/METADATA
frozen_soup-0.5.dist-info/WHEEL
frozen_soup-0.5.dist-info/top_level.txt
frozen_soup-0.5.dist-info/RECORD
