Metadata-Version: 2.1
Name: frozen-soup
Version: 0.5
Summary: Create a single-file version of an HTML file
Author: Jim Winstead
License: Apache-2.0
Project-URL: Homepage, https://github.com/jimwins/frozen-soup
Project-URL: Changelog, https://github.com/jimwins/frozen-soup/releases
Project-URL: Issues, https://github.com/jimwins/frozen-soup/issues
Project-URL: CI, https://github.com/jimwins/frozen-soup/actions
Classifier: License :: OSI Approved :: Apache Software License
Requires-Python: >=3.9
License-File: LICENSE
Requires-Dist: requests
Requires-Dist: beautifulsoup4
Requires-Dist: tinycss2
Provides-Extra: test
Requires-Dist: pytest ; extra == 'test'
Requires-Dist: requests-testadapter ; extra == 'test'
